venvstarter.py
_venvstarter/__init__.py
_venvstarter/errors.py
_venvstarter/helpers.py
_venvstarter/python_handler.py
_venvstarter/questions.py
_venvstarter/starter.py
_venvstarter/version.py
venvstarter-0.12.2.dist-info/METADATA
venvstarter-0.12.2.dist-info/WHEEL
venvstarter-0.12.2.dist-info/licenses/LICENSE
venvstarter-0.12.2.dist-info/RECORD
