Metadata-Version: 2.1
Name: venvstarter
Version: 0.12.2
Summary: Tool to create virtualenvs, manage versions of packages in it and use it start a particular program
Project-URL: Homepage, https://github.com/delfick/venvstarter
Author-email: Stephen Moore <github@delfick.com>
License-Expression: MIT
License-File: LICENSE
Requires-Python: >=3.7
Provides-Extra: tests
Requires-Dist: noseofyeti[black]==2.4.7; extra == 'tests'
Requires-Dist: pytest-helpers-namespace==2021.12.29; extra == 'tests'
Requires-Dist: pytest-parallel==0.1.1; extra == 'tests'
Requires-Dist: pytest>=7.2.0; extra == 'tests'
